CoronaTest/__init__.py
CoronaTest/ques_pickle
CoronaTest/sugg_pickle
CoronaTest/test.py
CoronaTest-1.8.dist-info/LICENSE
CoronaTest-1.8.dist-info/METADATA
CoronaTest-1.8.dist-info/WHEEL
CoronaTest-1.8.dist-info/top_level.txt
CoronaTest-1.8.dist-info/RECORD
