Metadata-Version: 2.1
Name: CoronaTest
Version: 1.8
Summary: UNKNOWN
Home-page: UNKNOWN
Author: Karigor
Author-email: 
License: MIT
Platform: UNKNOWN
Classifier: Programming Language :: Python :: 3
Classifier: License :: OSI Approved :: MIT License
Classifier: Operating System :: OS Independent
Requires-Dist: ConvertVal
